canopy_shade/__init__.py
canopy_shade/canopy_shade.py
canopy_shade/cli.py
canopy_shade/image_process.py
canopy_shade/solar_data_process.py
canopy_shade/visualization.py
canopy_shade-0.0.3.dist-info/AUTHORS.rst
canopy_shade-0.0.3.dist-info/LICENSE
canopy_shade-0.0.3.dist-info/METADATA
canopy_shade-0.0.3.dist-info/WHEEL
canopy_shade-0.0.3.dist-info/top_level.txt
canopy_shade-0.0.3.dist-info/RECORD
